LICENSE
README.md
setup.py
piped_api/__init__.py
piped_api/client.py
piped_api.egg-info/PKG-INFO
piped_api.egg-info/SOURCES.txt
piped_api.egg-info/dependency_links.txt
piped_api.egg-info/requires.txt
piped_api.egg-info/top_level.txt
piped_api/models/__init__.py
piped_api/models/channels.py
piped_api/models/comments.py
piped_api/models/videos.py