Metadata-Version: 2.1
Name: piped-api
Version: 1.0.1b0
Summary: Piped API client
Home-page: https://github.com/CWKevo/python-piped-api-client
Author: SKevo
Author-email: me@kevo.link
License: MIT
Keywords: piped,api,client
Platform: UNKNOWN
Classifier: Development Status :: 4 - Beta
Classifier: Intended Audience :: Developers
Classifier: License :: OSI Approved :: MIT License
Classifier: Programming Language :: Python :: 3.6
Classifier: Programming Language :: Python :: 3.7
Classifier: Programming Language :: Python :: 3.8
Classifier: Programming Language :: Python :: 3.9
Classifier: Programming Language :: Python :: 3.10
License-File: LICENSE
